agnmol/__init__.py
agnmol/motion.py
agnmol-1.0.9.dist-info/LICENSE.txt
agnmol-1.0.9.dist-info/METADATA
agnmol-1.0.9.dist-info/WHEEL
agnmol-1.0.9.dist-info/top_level.txt
agnmol-1.0.9.dist-info/RECORD
