Metadata-Version: 2.1
Name: agnmol
Version: 1.0.9
Summary: A package for physics motion calculations
Author-email: agnmol <agnmol@ktu.lt>
Classifier: Programming Language :: Python :: 3
Classifier: License :: OSI Approved :: MIT License
Classifier: Operating System :: OS Independent
Requires-Python: >=3.10
License-File: LICENSE.txt
